gcshus/__init__.py
gcshus/signed_url.py
gcshus/upload.py
gcshus-0.0.1.dist-info/LICENSE
gcshus-0.0.1.dist-info/METADATA
gcshus-0.0.1.dist-info/WHEEL
gcshus-0.0.1.dist-info/top_level.txt
gcshus-0.0.1.dist-info/RECORD
