Metadata-Version: 2.1
Name: gcshus
Version: 0.0.1
Summary: gcshus: GCS helper utils.
Home-page: https://github.com/yokoe/gcshus
Author: yokoe
Author-email: kreuz45@kreuz45.com
Maintainer: yokoe
Maintainer-email: kreuz45@kreuz45.com
License: MIT
Download-URL: https://github.com/yokoe/gcshus
Keywords: gcs
Platform: UNKNOWN
Classifier: License :: OSI Approved :: MIT License
Classifier: Programming Language :: Python :: 3.6
License-File: LICENSE
Requires-Dist: google-cloud-storage (==2.7.0)
